appleconnector/__init__.py
appleconnector/__main__.py
appleconnector/connector.py
appleconnector/connector_test.py
appleconnector-0.4.0.dist-info/LICENSE
appleconnector-0.4.0.dist-info/METADATA
appleconnector-0.4.0.dist-info/WHEEL
appleconnector-0.4.0.dist-info/entry_points.txt
appleconnector-0.4.0.dist-info/top_level.txt
appleconnector-0.4.0.dist-info/RECORD
