Metadata-Version: 2.1
Name: appleconnector
Version: 0.4.0
Summary: Apple Connector for Podcast Data
Author: Open Podcast
License: MIT
License-File: LICENSE
Requires-Dist: requests
Requires-Dist: loguru
Requires-Dist: PyYAML
Requires-Dist: tenacity
